POSM/__init__.py
POSM/config.txt
POSM/main.py
POSM/Changeset/Changeset.py
POSM/Changeset/ChangesetForm.py
POSM/Changeset/__init__.py
POSM/ElementsLoader/ElementsLoader.py
POSM/ElementsLoader/Node.py
POSM/ElementsLoader/__init__.py
POSM/GPXLoader/GPXLoader.py
POSM/GPXLoader/__init__.py
POSM/TileLoader/Tile.py
POSM/TileLoader/TileLoader.py
POSM/TileLoader/__init__.py
POSM/Viewer/ElementViewer.py
POSM/Viewer/LayerManager.py
POSM/Viewer/OSMCopyright.py
POSM/Viewer/Viewer.py
POSM/Viewer/__init__.py
POSM/utils/Point.py
POSM/utils/__init__.py
POSM/utils/calc.py
POSM/utils/config.py
POSM-0.1.5.3.dist-info/LICENSE
POSM-0.1.5.3.dist-info/METADATA
POSM-0.1.5.3.dist-info/WHEEL
POSM-0.1.5.3.dist-info/entry_points.txt
POSM-0.1.5.3.dist-info/top_level.txt
POSM-0.1.5.3.dist-info/RECORD
