Metadata-Version: 2.1
Name: POSM
Version: 0.1.5.3
Summary: UNKNOWN
Home-page: https://github.com/PhilippRigoll/POSM
Author: Philipp Rigoll
Author-email: philipp@rigoll.de
License: UNKNOWN
Platform: UNKNOWN
Requires-Python: >=3.6
Requires-Dist: numpy
Requires-Dist: Pillow
Requires-Dist: PyYAML
Requires-Dist: PySide2
Requires-Dist: easydict
Requires-Dist: lxml
Requires-Dist: requests
Requires-Dist: gpxpy
Requires-Dist: dataclasses ; python_version < "3.7"
